[
  {
    "id": "1.1",
    "name": "Golden Hour Kitchen, Wide",
    "generationId": "1f13c9bf-f15e-6b20-8f75-ef38e5d7b16c"
  },
  {
    "id": "10.3",
    "name": "The House",
    "generationId": "1f13c9c0-0704-6b00-8f69-12a46aaa413f"
  },
  {
    "id": "10.4",
    "name": "The House",
    "generationId": "1f13c9c0-1c29-6490-8753-da5fb5685dfe"
  },
  {
    "id": "6.2",
    "name": "The View FROM the Window, Exterior",
    "generationId": "1f13c9c0-31cf-6470-b9be-6b56a6d01d1f"
  },
  {
    "id": "4.1",
    "name": "Rilke on the Couch, Watching",
    "generationId": "1f13c9c0-464d-6dc0-878a-29bc01a98f17"
  },
  {
    "id": "10.5",
    "name": "Dan Character Portrait",
    "generationId": "1f13c9c0-5b3f-6300-a24c-6825dcaa2026"
  },
  {
    "id": "1.2",
    "name": "Morning Fog Kitchen, Wide",
    "generationId": "1f13c9c0-70b1-6e90-83f1-594aeb8f019e"
  },
  {
    "id": "8.1",
    "name": "Night Kitchen, Laptop Glow",
    "generationId": "1f13c9c0-8a4a-6a50-9966-910a93347b07"
  },
  {
    "id": "10.1",
    "name": "Through the Reeded Glass: Ryan Working",
    "generationId": "d6b4d8fe-6bb6-4c6f-a820-4cafb4ba6adc"
  },
  {
    "id": "10.2",
    "name": "The Deck at Dusk, Looking In",
    "generationId": "1f13c9c0-b3a2-6240-b86f-91adfefedc4a"
  },
  {
    "id": "1.3",
    "name": "Kitchen from Deck Entrance, Lena's POV",
    "generationId": "1f13c9c0-cfc9-62c0-abcf-de8d008f35a0"
  },
  {
    "id": "2.2",
    "name": "Two People at the Table, Medium Wide",
    "generationId": "5a10d849-ccff-4c53-8b2e-4a49fee85ddb"
  },
  {
    "id": "10.6",
    "name": "Lena",
    "generationId": "1f13c9c0-f8f4-6b90-9354-73b6d1fc6a65"
  }
]